auto_readme/__init__.py
auto_readme/cli.py
auto_readme/generator.py
auto_readme/templates/readme.md.j2
auto_research_readme-1.0.0.dist-info/METADATA
auto_research_readme-1.0.0.dist-info/WHEEL
auto_research_readme-1.0.0.dist-info/entry_points.txt
auto_research_readme-1.0.0.dist-info/top_level.txt
auto_research_readme-1.0.0.dist-info/RECORD
