Metadata-Version: 2.4
Name: auto-research-readme
Version: 1.0.0
Summary: Generate consistent, professional READMEs from YAML config
Home-page: https://github.com/Stratum-Research/auto-research-readme
Author: Abdullah Ridwan
Author-email: abdullahridwan@gmail.com
Keywords: readme documentation yaml config generator markdown
Classifier: Development Status :: 4 - Beta
Classifier: Intended Audience :: Developers
Classifier: License :: OSI Approved :: MIT License
Classifier: Programming Language :: Python :: 3
Classifier: Programming Language :: Python :: 3.8
Classifier: Programming Language :: Python :: 3.9
Classifier: Programming Language :: Python :: 3.10
Classifier: Programming Language :: Python :: 3.11
Classifier: Programming Language :: Python :: 3.12
Classifier: Topic :: Software Development :: Documentation
Classifier: Topic :: Text Processing :: Markup
Requires-Python: >=3.8
Requires-Dist: PyYAML>=6.0
Requires-Dist: Jinja2>=3.0
Dynamic: author
Dynamic: author-email
Dynamic: classifier
Dynamic: description
Dynamic: description-content-type
Dynamic: home-page
Dynamic: keywords
Dynamic: requires-dist
Dynamic: requires-python
Dynamic: summary
